LICENSE
README.md
pytest_socket.py
pytest_socket-0.5.1.dist-info/entry_points.txt
pytest_socket-0.5.1.dist-info/LICENSE
pytest_socket-0.5.1.dist-info/WHEEL
pytest_socket-0.5.1.dist-info/METADATA
pytest_socket-0.5.1.dist-info/RECORD
